oanda_v20_client/__init__.py
oanda_v20_client/client.py
oanda_v20_client/errors.py
oanda_v20_client/py.typed
oanda_v20_client/types.py
oanda_v20_client/api/__init__.py
oanda_v20_client/api/default/__init__.py
oanda_v20_client/api/default/cancel_order.py
oanda_v20_client/api/default/close_position.py
oanda_v20_client/api/default/close_trade.py
oanda_v20_client/api/default/configure_account.py
oanda_v20_client/api/default/create_order.py
oanda_v20_client/api/default/get_account.py
oanda_v20_client/api/default/get_account_changes.py
oanda_v20_client/api/default/get_account_instruments.py
oanda_v20_client/api/default/get_account_summary.py
oanda_v20_client/api/default/get_base_prices.py
oanda_v20_client/api/default/get_external_user_info.py
oanda_v20_client/api/default/get_instrument_candles.py
oanda_v20_client/api/default/get_instrument_price.py
oanda_v20_client/api/default/get_instrument_price_range.py
oanda_v20_client/api/default/get_instruments_instrument_order_book.py
oanda_v20_client/api/default/get_instruments_instrument_position_book.py
oanda_v20_client/api/default/get_order.py
oanda_v20_client/api/default/get_position.py
oanda_v20_client/api/default/get_prices.py
oanda_v20_client/api/default/get_trade.py
oanda_v20_client/api/default/get_transaction.py
oanda_v20_client/api/default/get_transaction_range.py
oanda_v20_client/api/default/get_transactions_since_id.py
oanda_v20_client/api/default/get_user_info.py
oanda_v20_client/api/default/list_accounts.py
oanda_v20_client/api/default/list_open_positions.py
oanda_v20_client/api/default/list_open_trades.py
oanda_v20_client/api/default/list_orders.py
oanda_v20_client/api/default/list_pending_orders.py
oanda_v20_client/api/default/list_positions.py
oanda_v20_client/api/default/list_trades.py
oanda_v20_client/api/default/list_transactions.py
oanda_v20_client/api/default/replace_order.py
oanda_v20_client/api/default/set_order_client_extensions.py
oanda_v20_client/api/default/set_trade_client_extensions.py
oanda_v20_client-0.2.0.dist-info/METADATA
oanda_v20_client-0.2.0.dist-info/WHEEL
oanda_v20_client-0.2.0.dist-info/RECORD
