Metadata-Version: 2.3
Name: oanda-v20-client
Version: 0.2.0
Summary: A client library for accessing OANDA v20 REST API
Author-email: Takin Profit LLC <takinprofit@gmail.com>
License: MIT License
Requires-Python: >=3.10
Requires-Dist: attrs>=21.3.0
Requires-Dist: dacite>=1.8.1
Requires-Dist: httpx<0.28.0,>=0.20.0
Requires-Dist: python-dateutil>=2.8.0
